{
    "1":{
        "name":"Strength",
        "shorthand":"str",
        "stats":[
            {
                "min":5,
                "max":20,
                "range":15,
                "step":0.15,
                "type":"",
                "emoji":"",
                "unit":"%",
                "digits":5
            }
        ],
        "description":"Increases your :STR:STR by [stat]"
    },"2":{
        "name":"Magic",
        "shorthand":"mag",
        "stats":[
            {
                "min":5,
                "max":20,
                "range":15,
                "step":0.15,
                "type":"",
                "emoji":"",
                "unit":"%",
                "digits":5
            }
        ],
        "description":"Increases your :MAG:MAG by [stat]"
    },"3":{
        "name":"Health Point",
        "shorthand":"hp",
        "stats":[
            {
                "min":5,
                "max":20,
                "range":15,
                "step":0.15,
                "type":"",
                "emoji":"",
                "unit":"%",
                "digits":5
            }
        ],
        "description":"Increases your :HP:HP by [stat]"
    },"4":{
        "name":"Weapon Point",
        "shorthand":"wp",
        "stats":[
            {
                "min":10,
                "max":30,
                "range":20,
                "step":0.2,
                "type":"",
                "emoji":"",
                "unit":"%",
                "digits":4
            }
        ],
        "description":"Increases your :WP:WP by [stat]"
    },"5":{
        "name":"Physical Resistance",
        "shorthand":"pr",
        "stats":[
            {
                "min":15,
                "max":35,
                "range":20,
                "step":0.2,
                "type":"",
                "emoji":"",
                "unit":"%",
                "digits":4
            }
        ],
        "description":"Increases your :iPR:iPR by [stat]"
    },"6":{
        "name":"Magical Resistance",
        "shorthand":"mr",
        "stats":[
            {
                "min":15,
                "max":35,
                "range":20,
                "step":0.2,
                "type":"",
                "emoji":"",
                "unit":"%",
                "digits":4
            }
        ],
        "description":"Increases your :iMR:iMR by [stat]"
    },"7":{
        "name":"Lifesteal",
        "shorthand":"ls",
        "stats":[
            {
                "min":15,
                "max":35,
                "range":20,
                "step":0.2,
                "type":"",
                "emoji":"",
                "unit":"%",
                "digits":4
            }
        ],
        "description":"All damage you deal heals you for [stat] of the damage dealt!"
    },"8":{
        "name":"Thorns",
        "shorthand":"th",
        "stats":[
            {
                "min":15,
                "max":35,
                "range":20,
                "step":0.2,
                "type":"",
                "emoji":"",
                "unit":"%",
                "digits":4
            }
        ],
        "description":"Reflect [stat] of the damage dealt to you as true damage"
    },"9":{
        "name":"Mana Tap",
        "shorthand":"mtap",
        "stats":[
            {
                "min":15,
                "max":30,
                "range":15,
                "step":0.15,
                "type":"",
                "emoji":"",
                "unit":"%",
                "digits":5
            }
        ],
        "description":"All damage you deal replenishes your :WP:WP for [stat] of the damage dealt!"
    },"10":{
        "name":"Absolve",
        "shorthand":"absv",
        "stats":[
            {
                "min":60,
                "max":80,
                "range":20,
                "step":0.2,
                "type":"",
                "emoji":"",
                "unit":"%",
                "digits":4
            }
        ],
        "description":"When healed, deal [stat] of the healed amount to a random enemy as :MAG:MAG damage"
    },"11":{
        "name":"Safeguard",
        "shorthand":"sg",
        "stats":[
            {
                "min":20,
                "max":40,
                "range":20,
                "step":0.2,
                "type":"",
                "emoji":"",
                "unit":"%",
                "digits":4
            }
        ],
        "description":"Negate [stat] of the damage dealt to you with :WP:WP"
    },"12":{
        "name":"Critical",
        "shorthand":"crit",
        "stats":[
            {
                "min":10,
                "max":30,
                "range":20,
                "step":0.2,
                "type":"",
                "emoji":"",
                "unit":"%",
                "digits":4
            },{
                "min":25,
                "max":50,
                "range":25,
                "step":0.25,
                "type":"",
                "emoji":"",
                "unit":"%",
                "digits":5
            }
        ],
        "description":"Every attack has a [stat] chance to deal [stat] more damage. This can apply to heals."
    },"13":{
        "name":"Discharge",
        "shorthand":"dc",
        "stats":[
            {
                "min":100,
                "max":140,
                "range":40,
                "step":0.4,
                "type":"",
                "emoji":"",
                "unit":"%",
                "digits":5
            }
        ],
        "description":"When :WP:WP is replenished, deal [stat] of the replenished amount to a random enemy as :MAG:MAG damage"
    },"14":{
        "name":"Kamikaze",
        "shorthand":"kkaze",
        "stats":[
            {
                "min":50,
                "max":75,
                "range":25,
                "step":0.25,
                "type":"",
                "emoji":"",
                "unit":"%",
                "digits":5
            }
        ],
        "description":"When the animal dies, deal [stat] of its max :HP:HP as :MAG:MAG dmg to the attacker"
    },"15":{
        "name":"Regeneration",
        "shorthand":"hgen",
        "stats":[
            {
                "min":5,
                "max":10,
                "range":5,
                "step":0.05,
                "type":"",
                "emoji":"",
                "unit":"%",
                "digits":5
            }
        ],
        "description":"Heal [stat] of your max :HP:HP after every turn"
    },"16":{
        "name":"Energize",
        "shorthand":"wgen",
        "stats":[
            {
                "min":20,
                "max":40,
                "range":20,
                "step":0.2,
                "type":"",
                "emoji":"",
                "unit":"",
                "digits":4
            }
        ],
        "description":"Replenish [stat] :WP:WP after every turn"
    },"17":{
        "name":"Sprout",
        "shorthand":"sprout",
        "stats":[
            {
                "min":20,
                "max":40,
                "range":20,
                "step":0.2,
                "type":"",
                "emoji":"",
                "unit":"%",
                "digits":4
            }
        ],
        "description":"Increase all incoming healing by [stat]"
    },"18":{
        "name":"Enrage",
        "shorthand":"enrage",
        "stats":[
            {
                "min":1,
                "max":4,
                "range":3,
                "step":0.03,
                "type":"",
                "emoji":"",
                "unit":"%",
                "digits":4
            }
        ],
        "description":"Every 10% of missing health gives [stat] extra damage"
    },"19":{
        "name":"Sacrifice",
        "shorthand":"sac",
        "stats":[
            {
                "min":50,
                "max":75,
                "range":25,
                "step":0.25,
                "type":"",
                "emoji":"",
                "unit":"%",
                "digits":5
            },{
                "min":50,
                "max":75,
                "range":25,
                "step":0.25,
                "type":"",
                "emoji":"",
                "unit":"%",
                "digits":5
            }
        ],
        "description":"When this animal dies, heal your teammates for [stat] of its Max :HP:HP and replenish for [stat] of its Max :WP:WP"
    },"20":{
        "name":"Snail",
        "shorthand":"snail",
        "stats":[
            {
                "min":5,
                "max":15,
                "range":10,
                "step":0.1,
                "type":"",
                "emoji":"",
                "unit":"%",
                "digits":4
            }
        ],
        "description":"Your pet snail fights with you. Whenever you attack an animal, snail will slap a random enemy for [stat] of the damage dealt."
    },"21":{
        "name":"Knowledge",
        "shorthand":"kno",
        "stats":[
            {
                "min":5,
                "max":15,
                "range":10,
                "step":0.1,
                "type":"",
                "emoji":"",
                "unit":"%",
                "digits":4
            }
        ],
        "description":"This passive does not do anything in battle. However, it will give this animal [stat] extra xp after each battle."
    }
}